uniquex-0.0.0.dist-info/METADATA
uniquex-0.0.0.dist-info/WHEEL
uniquex/__init__.py
uniquex/py.typed
uniquex-0.0.0.dist-info/RECORD
