Metadata-Version: 2.1
Name: uniquex
Version: 0.0.0
Summary: UniqueX - your almighty API client.
Keywords: development,rest,httpx,api,client,openapi
Author-Email: Oleh Mazur <oleh@four-velocity.com>
License: MIT
Classifier: Development Status :: 1 - Planning
Classifier: Environment :: Web Environment
Classifier: Framework :: AsyncIO
Classifier: Framework :: Pydantic :: 2
Classifier: Framework :: Trio
Classifier: Intended Audience :: Developers
Classifier: License :: OSI Approved :: MIT License
Classifier: Operating System :: OS Independent
Classifier: Programming Language :: Python :: 3.10
Classifier: Programming Language :: Python :: 3.11
Classifier: Programming Language :: Python :: 3.12
Classifier: Topic :: Internet :: WWW/HTTP
Classifier: Typing :: Typed
Requires-Python: >=3.10
Requires-Dist: httpx>=0.27.2
Requires-Dist: typer>=0.12.5
Requires-Dist: pyyaml>=6.0.2
Requires-Dist: pydantic!=2.0.0,!=2.0.1,<3.0.0,>2.0.0
